minject/README.md
minject/__init__.py
minject/config.py
minject/inject.py
minject/inject_attrs.py
minject/metadata.py
minject/mock.py
minject/model.py
minject/mypy_plugin.py
minject/py.typed
minject/registry.py
minject/types.py
minject-1.5.0.dist-info/METADATA
minject-1.5.0.dist-info/WHEEL
minject-1.5.0.dist-info/licenses/LICENSE
minject-1.5.0.dist-info/RECORD
