Metadata-Version: 2.4
Name: minject
Version: 1.5.0
Summary: A small dependency injection library for Python.
Author-email: Matt McHenry <mmchenry@duolingo.com>, Alek Binion <alek@duolingo.com>, Xiyan Shao <xiyan@duolingo.com>, Service Framework Team <service-framework-team@duolingo.com>
License:                                  Apache License
License-File: LICENSE
Classifier: Development Status :: 5 - Production/Stable
Requires-Python: >=3.9
Requires-Dist: attrs>=17.4
Requires-Dist: packaging
Requires-Dist: typing-extensions>=4.1
